[
  {
    "title": "The Bonfire of the Manatees",
    "code": "S17E01"
  },
  {
    "title": "The Girl Who Slept Too Little",
    "code": "S17E02"
  },
  {
    "title": "Milhouse of Sand and Fog",
    "code": "S17E03"
  },
  {
    "title": "Treehouse of Horror XVI",
    "code": "S17E04"
  },
  {
    "title": "Marge's Son Poisoning",
    "code": "S17E05"
  },
  {
    "title": "See Homer Run",
    "code": "S17E06"
  },
  {
    "title": "The Last of the Red Hat Mamas",
    "code": "S17E07"
  },
  {
    "title": "The Italian Bob",
    "code": "S17E08"
  },
  {
    "title": "Simpsons Christmas Stories",
    "code": "S17E09"
  },
  {
    "title": "Homer's Paternity Coot",
    "code": "S17E10"
  },
  {
    "title": "We're on the Road to D'oh-where",
    "code": "S17E11"
  },
  {
    "title": "My Fair Laddy",
    "code": "S17E12"
  },
  {
    "title": "The Seemingly Never-Ending Story",
    "code": "S17E13"
  },
  {
    "title": "Bart Has Two Mommies",
    "code": "S17E14"
  },
  {
    "title": "Homer Simpson, This Is Your Wife",
    "code": "S17E15"
  },
  {
    "title": "Million-Dollar Abie",
    "code": "S17E16"
  },
  {
    "title": "Kiss Kiss Bang Bangalore",
    "code": "S17E17"
  },
  {
    "title": "The Wettest Stories Ever Told",
    "code": "S17E18"
  },
  {
    "title": "Girls Just Want to Have Sums",
    "code": "S17E19"
  },
  {
    "title": "Regarding Margie",
    "code": "S17E20"
  },
  {
    "title": "The Monkey Suit",
    "code": "S17E21"
  },
  {
    "title": "Marge and Homer Turn a Couple Play",
    "code": "S17E22"
  }
]
